bcodata/__init__.py
bcodata/client.py
bcodata/exceptions.py
bcodata/py.typed
bcodata/query.py
bcodata-0.1.3.dist-info/METADATA
bcodata-0.1.3.dist-info/WHEEL
bcodata-0.1.3.dist-info/licenses/LICENSE
bcodata-0.1.3.dist-info/RECORD
