Metadata-Version: 2.4
Name: bcodata
Version: 0.1.3
Summary: Add your description here
Author-email: akshpra <210279575+akshaypra26@users.noreply.github.com>
License-File: LICENSE
Requires-Python: >=3.12
Requires-Dist: aiolimiter>=1.2.1
Requires-Dist: httpx>=0.28.1
Requires-Dist: loguru>=0.7.3
Requires-Dist: tenacity>=9.1.2
